qsmap/__init__.py
qsmap/config.py
qsmap/core.py
qsmap/elevation.py
qsmap/overpass.py
qsmap/routing.py
qsmap/tile.py
qsmap/utils.py
qsmap-1.0.0.dist-info/METADATA
qsmap-1.0.0.dist-info/WHEEL
qsmap-1.0.0.dist-info/top_level.txt
qsmap-1.0.0.dist-info/RECORD
