Metadata-Version: 2.1
Name: qsmap
Version: 1.0.0
Summary: Package provides functionality for working with geographical data, routing, and mapping
Home-page: https://github.com/saferide-tech/QuestarMap
Author: Yaroslav Mavliutov
Author-email: yaroslavm@questarauto.com
License: MIT
Keywords: geo,routing,mapping
Requires-Dist: anyio ==4.2.0
Requires-Dist: appnope ==0.1.3
Requires-Dist: argon2-cffi ==23.1.0
Requires-Dist: argon2-cffi-bindings ==21.2.0
Requires-Dist: arrow ==1.3.0
Requires-Dist: asttokens ==2.4.1
Requires-Dist: async-lru ==2.0.4
Requires-Dist: attrs ==23.2.0
Requires-Dist: Babel ==2.14.0
Requires-Dist: beautifulsoup4 ==4.12.3
Requires-Dist: bleach ==6.1.0
Requires-Dist: branca ==0.7.0
Requires-Dist: certifi ==2023.11.17
Requires-Dist: cffi ==1.16.0
Requires-Dist: charset-normalizer ==3.3.2
Requires-Dist: comm ==0.2.1
Requires-Dist: debugpy ==1.8.0
Requires-Dist: decorator ==5.1.1
Requires-Dist: defusedxml ==0.7.1
Requires-Dist: executing ==2.0.1
Requires-Dist: fastjsonschema ==2.19.1
Requires-Dist: folium ==0.15.1
Requires-Dist: fqdn ==1.5.1
Requires-Dist: idna ==3.6
Requires-Dist: ipykernel ==6.29.0
Requires-Dist: ipython ==8.20.0
Requires-Dist: isoduration ==20.11.0
Requires-Dist: jedi ==0.19.1
Requires-Dist: Jinja2 ==3.1.3
Requires-Dist: json5 ==0.9.14
Requires-Dist: jsonpointer ==2.4
Requires-Dist: jsonschema ==4.21.1
Requires-Dist: jsonschema-specifications ==2023.12.1
Requires-Dist: jupyter-events ==0.9.0
Requires-Dist: jupyter-lsp ==2.2.2
Requires-Dist: jupyter-client ==8.6.0
Requires-Dist: jupyter-core ==5.7.1
Requires-Dist: jupyter-server ==2.12.5
Requires-Dist: jupyter-server-terminals ==0.5.2
Requires-Dist: jupyterlab ==4.0.11
Requires-Dist: jupyterlab-pygments ==0.3.0
Requires-Dist: jupyterlab-server ==2.25.2
Requires-Dist: MarkupSafe ==2.1.4
Requires-Dist: matplotlib-inline ==0.1.6
Requires-Dist: mistune ==3.0.2
Requires-Dist: nbclient ==0.9.0
Requires-Dist: nbconvert ==7.14.2
Requires-Dist: nbformat ==5.9.2
Requires-Dist: nest-asyncio ==1.6.0
Requires-Dist: notebook ==7.0.7
Requires-Dist: notebook-shim ==0.2.3
Requires-Dist: numpy ==1.26.3
Requires-Dist: overpy ==0.7
Requires-Dist: overrides ==7.7.0
Requires-Dist: packaging ==23.2
Requires-Dist: pandas ==2.2.0
Requires-Dist: pandocfilters ==1.5.1
Requires-Dist: parso ==0.8.3
Requires-Dist: pexpect ==4.9.0
Requires-Dist: platformdirs ==4.1.0
Requires-Dist: polyline ==2.0.1
Requires-Dist: prometheus-client ==0.19.0
Requires-Dist: prompt-toolkit ==3.0.43
Requires-Dist: psutil ==5.9.8
Requires-Dist: ptyprocess ==0.7.0
Requires-Dist: pure-eval ==0.2.2
Requires-Dist: py4j ==0.10.9.7
Requires-Dist: pycparser ==2.21
Requires-Dist: Pygments ==2.17.2
Requires-Dist: pyspark ==3.5.0
Requires-Dist: python-dateutil ==2.8.2
Requires-Dist: python-json-logger ==2.0.7
Requires-Dist: pytz ==2023.4
Requires-Dist: PyYAML ==6.0.1
Requires-Dist: pyzmq ==25.1.2
Requires-Dist: referencing ==0.33.0
Requires-Dist: requests ==2.31.0
Requires-Dist: rfc3339-validator ==0.1.4
Requires-Dist: rfc3986-validator ==0.1.1
Requires-Dist: rpds-py ==0.17.1
Requires-Dist: Send2Trash ==1.8.2
Requires-Dist: six ==1.16.0
Requires-Dist: sniffio ==1.3.0
Requires-Dist: soupsieve ==2.5
Requires-Dist: stack-data ==0.6.3
Requires-Dist: terminado ==0.18.0
Requires-Dist: tinycss2 ==1.2.1
Requires-Dist: tornado ==6.4
Requires-Dist: traitlets ==5.14.1
Requires-Dist: types-python-dateutil ==2.8.19.20240106
Requires-Dist: tzdata ==2023.4
Requires-Dist: uri-template ==1.3.0
Requires-Dist: urllib3 ==2.1.0
Requires-Dist: wcwidth ==0.2.13
Requires-Dist: webcolors ==1.13
Requires-Dist: webencodings ==0.5.1
Requires-Dist: websocket-client ==1.7.0
Requires-Dist: xmltodict ==0.13.0
Requires-Dist: xyzservices ==2023.10.1
